{
  "data": {
    "lesson": {
      "_id": "63eb9a79194b225c77e5f536",
      "title": " Multithreading quiz",
      "courseId": "63a2eb428899436daf7eb489",
      "quizQuestions": [
        {
          "_id": "63eb9a79194b226ff2e5f537",
          "title": "<p>&nbsp;What is multithreading in Python?</p>",
          "options": [
            {
              "name": "<p>&nbsp;A process of running multiple threads simultaneously within a single process.</p>"
            },
            {
              "name": "<p>&nbsp;A process of running multiple processes simultaneously within a single thread</p>"
            },
            {
              "name": "<p>A process of running multiple processes simultaneously within multiple threads.</p>"
            },
            {
              "name": "<p>A process of running a single process within multiple threads.</p><p>&nbsp;</p>"
            }
          ]
        },
        {
          "_id": "63eb9a79194b22b349e5f538",
          "title": "<p>What is the purpose of multithreading in Python?</p>",
          "options": [
            {
              "name": "<p>&nbsp;To improve the performance of a program by using multiple CPUs or CPU cores.</p>"
            },
            {
              "name": "<p>&nbsp;To improve the memory utilization of a program by using multiple CPUs or CPU cores.</p>"
            },
            {
              "name": "<p>To improve the overall efficiency of a program by using multiple CPUs or CPU cores.</p>"
            },
            {
              "name": "<p>&nbsp;To improve the input/output operations of a program by using multiple CPUs or CPU cores.</p>"
            }
          ]
        },
        {
          "_id": "63eb9a79194b220dd1e5f539",
          "title": "<p>&nbsp;Which module is used to create and manage threads in Python?</p>",
          "options": [
            {
              "name": "<p>&nbsp;threading</p>"
            },
            {
              "name": "<p>&nbsp;multiprocessing</p>"
            },
            {
              "name": "<p>&nbsp;concurrent.futures</p>"
            },
            {
              "name": "<p>queue</p>"
            }
          ]
        },
        {
          "_id": "63eb9a79194b22c712e5f53a",
          "title": "<p>What is a mutex in multithreading?</p>",
          "options": [
            {
              "name": "<p>A type of thread that performs a specific task.</p>"
            },
            {
              "name": "<p>&nbsp;A type of thread that runs in the background to handle incoming requests.</p>"
            },
            {
              "name": "<p>&nbsp;A synchronization primitive used to protect shared resources from being accessed by multiple threads at the same time.</p>"
            },
            {
              "name": "<p>A built-in function in Python that is used to release the Global Interpreter Lock.</p>"
            }
          ]
        },
        {
          "_id": "63eb9a79194b228fe6e5f53b",
          "title": "<p>&nbsp;Which method is used to start a new thread in Python?</p>",
          "options": [
            {
              "name": "<p>&nbsp;start()</p>"
            },
            {
              "name": "<p>&nbsp;run()</p>"
            },
            {
              "name": "<p>create()</p>"
            },
            {
              "name": "<p>&nbsp;begin()</p>"
            }
          ]
        },
        {
          "_id": "63eb9a79194b2204a0e5f53c",
          "title": "<p>&nbsp;What is the Global Interpreter Lock (GIL) in Python?</p>",
          "options": [
            {
              "name": "<p>&nbsp;A lock used to protect shared resources from being accessed by multiple threads at the same time.</p>"
            },
            {
              "name": "<p>&nbsp;A mechanism used by Python to ensure that only one thread executes Python bytecode at a time.</p>"
            },
            {
              "name": "<p>&nbsp;A thread that runs in the background to handle incoming requests.</p>"
            },
            {
              "name": "<p>A type of thread that performs a specific task.</p>"
            }
          ]
        }
      ],
      "type": "quiz",
      "resources": [],
      "createdAt": "2023-02-14T14:28:09.119Z",
      "updatedAt": "2023-02-14T14:40:52.248Z",
      "__v": 0
    }
  }
}