{
  "data": {
    "lesson": {
      "_id": "63f22aedff47663c05dc9c93",
      "courseId": "63a2eb428899436daf7eb489",
      "data": {
        "maxPoints": 50,
        "url": "https://drive.google.com/file/d/1RhuY31tBf5fbYGmzBZizvCL0B3n8h-Xl/view?usp=sharing"
      },
      "title": "Flask Assignment-1",
      "type": "assignment",
      "resources": [],
      "quizQuestions": [],
      "createdAt": "2023-02-19T13:58:05.680Z",
      "updatedAt": "2023-02-25T08:55:17.939Z",
      "__v": 0
    }
  }
}